{
  "id": "q_item234_001",
  "item": 234,
  "specialite": "cardiologie",
  "partie": "ic-dyspnee",
  "tags": ["IC", "OAP", "traitement", "contre-indication", "betabloquants", "urgence", "rangA"],
  "rang": "A",
  "question": "Quel traitement est formellement contre-indiqué en phase aiguë initiale d'un œdème aigu pulmonaire (OAP) cardiogénique ?",
  "propositions": {
    "A": "Furosémide IV 40–80 mg",
    "B": "Dérivés nitrés IV",
    "C": "Ventilation non invasive (VNI)",
    "D": "Bêtabloquants",
    "E": "Position demi-assise"
  },
  "reponses": ["D"],
  "correction": "Les bêtabloquants sont formellement CONTRE-INDIQUÉS en phase aiguë d'OAP. Leur effet inotrope négatif aggrave la dysfonction ventriculaire et le bas débit cardiaque. En revanche : Furosémide IV (1ère intention, diurèse rapide), dérivés nitrés IV (réduction précharge par vasodilatation veineuse), VNI-CPAP (si SpO₂ < 90% malgré O₂) et position demi-assise sont tous indiqués. Les bêtabloquants sont réintroduits à distance, une fois la décompensation stabilisée."
}
